regexmodel/__init__.py
regexmodel/_version.py
regexmodel/datastructure.py
regexmodel/model.py
regexmodel/py.typed
regexmodel/regexclass.py
regexmodel/util.py
regexmodel/visualization.py
regexmodel-0.3.5.dist-info/LICENSE
regexmodel-0.3.5.dist-info/METADATA
regexmodel-0.3.5.dist-info/WHEEL
regexmodel-0.3.5.dist-info/top_level.txt
regexmodel-0.3.5.dist-info/RECORD
