Metadata-Version: 2.1
Name: regexmodel
Version: 0.3.5
Summary: Package modeling structured strings with regex.
Author-email: Raoul Schram <r.d.schram@uu.nl>
License: MIT License
Project-URL: GitHub, https://github.com/sodascience/regexmodel
Keywords: regex,fitting,modeling,statistics
Classifier: Programming Language :: Python :: 3
Classifier: Programming Language :: Python :: 3.8
Classifier: Programming Language :: Python :: 3.9
Classifier: Programming Language :: Python :: 3.10
Classifier: Programming Language :: Python :: 3.11
Classifier: Programming Language :: Python :: 3.12
Classifier: Development Status :: 3 - Alpha
Classifier: License :: OSI Approved :: MIT License
Requires-Python: >=3.8
License-File: LICENSE
Requires-Dist: polars >=0.19.8
Requires-Dist: numpy >=1.20
Provides-Extra: test
Requires-Dist: pytest ; extra == 'test'
Requires-Dist: pylint ; extra == 'test'
Requires-Dist: pydocstyle ; extra == 'test'
Requires-Dist: mypy ; extra == 'test'
Requires-Dist: ruff ; extra == 'test'
Requires-Dist: nbval ; extra == 'test'
Provides-Extra: tutorial
Requires-Dist: pyvis ; extra == 'tutorial'
Requires-Dist: networkx ; extra == 'tutorial'
Requires-Dist: faker ; extra == 'tutorial'
